validkit/__init__.py
validkit/client.py
validkit/config.py
validkit/exceptions.py
validkit/models.py
validkit-1.1.0.dist-info/LICENSE
validkit-1.1.0.dist-info/METADATA
validkit-1.1.0.dist-info/WHEEL
validkit-1.1.0.dist-info/top_level.txt
validkit-1.1.0.dist-info/RECORD
